mythic_c2_container/C2ProfileBase.py
mythic_c2_container/MythicRPC.py
mythic_c2_container/__init__.py
mythic_c2_container/config.py
mythic_c2_container/mythic_service.py
mythic_c2_container-0.0.31.dist-info/METADATA
mythic_c2_container-0.0.31.dist-info/WHEEL
mythic_c2_container-0.0.31.dist-info/top_level.txt
mythic_c2_container-0.0.31.dist-info/RECORD
