Metadata-Version: 2.1
Name: mythic-c2-container
Version: 0.0.31
Summary: Functionality for Mythic C2 Containers
Home-page: https://docs.mythic-c2.net/customizing/c2-related-development
Author: @its_a_feature_
Author-email: 
License: BSD3
Platform: UNKNOWN
Classifier: License :: Other/Proprietary License
Classifier: Programming Language :: Python :: 3
Classifier: Programming Language :: Python :: 3.8
Requires-Dist: aio-pika (==6.8.0)
Requires-Dist: dynaconf
Requires-Dist: psutil
